Metadata-Version: 2.1
Name: sweetmatch
Version: 0.1.0
Summary: UNKNOWN
Home-page: https://gitlab.com/jldez/sweetmatch
Author: Jean-Luc Déziel
Author-email: jluc1011@hotmail.com
License: UNKNOWN
Platform: UNKNOWN
